chibi_nginx/__init__.py
chibi_nginx/nginx.py
chibi_nginx-0.2.2.dist-info/AUTHORS.rst
chibi_nginx-0.2.2.dist-info/LICENSE
chibi_nginx-0.2.2.dist-info/METADATA
chibi_nginx-0.2.2.dist-info/WHEEL
chibi_nginx-0.2.2.dist-info/top_level.txt
chibi_nginx-0.2.2.dist-info/RECORD
