Metadata-Version: 2.1
Name: chibi_nginx
Version: 0.2.2
Summary: python lib for parse nginx conf files
Home-page: https://github.com/dem4ply/chibi_nginx
Author: dem4ply
Author-email: dem4ply@gmail.com
License: WTFPL
Keywords: chibi_nginx
Classifier: Development Status :: 2 - Pre-Alpha
Classifier: Intended Audience :: Developers
Classifier: License :: Public Domain
Classifier: Natural Language :: English
Classifier: Programming Language :: Python :: 3.7
Classifier: Programming Language :: Python :: 3.8
License-File: LICENSE
License-File: AUTHORS.rst
Requires-Dist: chibi >=0.11.7
